fast_mvgc/__init__.py
fast_mvgc/core.py
fast_mvgc/cpu_engine.py
fast_mvgc/utils.py
pytorch_mvgc-0.1.0.dist-info/LICENSE
pytorch_mvgc-0.1.0.dist-info/METADATA
pytorch_mvgc-0.1.0.dist-info/WHEEL
pytorch_mvgc-0.1.0.dist-info/top_level.txt
pytorch_mvgc-0.1.0.dist-info/RECORD
