Metadata-Version: 2.1
Name: pytorch-mvgc
Version: 0.1.0
Summary: A GPU-accelerated Multivariate Granger Causality implementation using PyTorch.
Home-page: https://github.com/yourusername/pytorch-mvgc
Author: nju_sit_hubc
Author-email: 2515094316@qq.com
Classifier: Programming Language :: Python :: 3
Classifier: License :: OSI Approved :: MIT License
Classifier: Operating System :: OS Independent
Requires-Python: >=3.6
License-File: LICENSE
Requires-Dist: numpy
Requires-Dist: torch>=1.9.0
Requires-Dist: tqdm
